<?xml version="1.0" encoding="UTF-8"?>
<GenRun Id="synth_1" LaunchPart="xc7z020clg400-1" LaunchTime="1717838062" LaunchIncrCheckpoint="$PSRCDIR/utils_1/imports/synth_1/Block_correctionV2_wrapper.dcp">
  <File Type="PA-TCL" Name="Block_correctionV2_wrapper.tcl"/>
  <File Type="RDS-PROPCONSTRS" Name="Block_correctionV2_wrapper_drc_synth.rpt"/>
  <File Type="REPORTS-TCL" Name="Block_correctionV2_wrapper_reports.tcl"/>
  <File Type="RDS-RDS" Name="Block_correctionV2_wrapper.vds"/>
  <File Type="RDS-UTIL" Name="Block_correctionV2_wrapper_utilization_synth.rpt"/>
  <File Type="RDS-UTIL-PB" Name="Block_correctionV2_wrapper_utilization_synth.pb"/>
  <File Type="RDS-DCP" Name="Block_correctionV2_wrapper.dcp"/>
  <File Type="VDS-TIMINGSUMMARY" Name="Block_correctionV2_wrapper_timing_summary_synth.rpt"/>
  <File Type="VDS-TIMING-PB" Name="Block_correctionV2_wrapper_timing_summary_synth.pb"/>
  <FileSet Name="sources" Type="DesignSrcs" RelSrcDir="$PSRCDIR/sources_1" RelGenDir="$PGENDIR/sources_1">
    <Filter Type="Srcs"/>
    <File Path="$PSRCDIR/sources_1/new/find_error.vhd">
      <FileInfo>
        <Attr Name="UsedIn" Val="synthesis"/>
        <Attr Name="UsedIn" Val="simulation"/>
      </FileInfo>
    </File>
    <File Path="$PSRCDIR/sources_1/new/correct_error.vhd">
      <FileInfo>
        <Attr Name="UsedIn" Val="synthesis"/>
        <Attr Name="UsedIn" Val="simulation"/>
      </FileInfo>
    </File>
    <File Path="$PSRCDIR/sources_1/new/calc_parity.vhd">
      <FileInfo>
        <Attr Name="UsedIn" Val="synthesis"/>
        <Attr Name="UsedIn" Val="simulation"/>
      </FileInfo>
    </File>
    <File Path="$PSRCDIR/sources_1/new/Input_memmory.vhd">
      <FileInfo>
        <Attr Name="UsedIn" Val="synthesis"/>
        <Attr Name="UsedIn" Val="simulation"/>
      </FileInfo>
    </File>
    <File Path="$PSRCDIR/sources_1/new/Output_memmory.vhd">
      <FileInfo>
        <Attr Name="UsedIn" Val="synthesis"/>
        <Attr Name="UsedIn" Val="simulation"/>
      </FileInfo>
    </File>
    <File Path="$PSRCDIR/sources_1/new/ControllerV2.vhd">
      <FileInfo>
        <Attr Name="UsedIn" Val="synthesis"/>
        <Attr Name="UsedIn" Val="simulation"/>
      </FileInfo>
    </File>
    <File Path="$PSRCDIR/sources_1/bd/Block_correctionV2/Block_correctionV2.bd">
      <FileInfo>
        <Attr Name="UsedIn" Val="synthesis"/>
        <Attr Name="UsedIn" Val="implementation"/>
        <Attr Name="UsedIn" Val="simulation"/>
      </FileInfo>
    </File>
    <File Path="$PGENDIR/sources_1/bd/Block_correctionV2/hdl/Block_correctionV2_wrapper.v">
      <FileInfo>
        <Attr Name="UsedIn" Val="synthesis"/>
        <Attr Name="UsedIn" Val="implementation"/>
        <Attr Name="UsedIn" Val="simulation"/>
      </FileInfo>
    </File>
    <File Path="$PSRCDIR/sources_1/new/Controller.vhd">
      <FileInfo>
        <Attr Name="AutoDisabled" Val="1"/>
        <Attr Name="UsedIn" Val="synthesis"/>
        <Attr Name="UsedIn" Val="simulation"/>
      </FileInfo>
    </File>
    <File Path="$PSRCDIR/sources_1/bd/block_correction/block_correction.bd">
      <FileInfo>
        <Attr Name="AutoDisabled" Val="1"/>
        <Attr Name="UsedIn" Val="synthesis"/>
        <Attr Name="UsedIn" Val="implementation"/>
        <Attr Name="UsedIn" Val="simulation"/>
      </FileInfo>
    </File>
    <File Path="$PGENDIR/sources_1/bd/block_correction/hdl/block_correction_wrapper.v">
      <FileInfo>
        <Attr Name="AutoDisabled" Val="1"/>
        <Attr Name="UsedIn" Val="synthesis"/>
        <Attr Name="UsedIn" Val="implementation"/>
        <Attr Name="UsedIn" Val="simulation"/>
      </FileInfo>
    </File>
    <File Path="$PSRCDIR/sources_1/new/FSK_Block_correction.vhd">
      <FileInfo>
        <Attr Name="AutoDisabled" Val="1"/>
        <Attr Name="UsedIn" Val="synthesis"/>
        <Attr Name="UsedIn" Val="simulation"/>
      </FileInfo>
    </File>
    <File Path="$PSRCDIR/sources_1/bd/Demodulator_over/Demodulator_over.bd">
      <FileInfo>
        <Attr Name="AutoDisabled" Val="1"/>
        <Attr Name="UsedIn" Val="synthesis"/>
        <Attr Name="UsedIn" Val="implementation"/>
        <Attr Name="UsedIn" Val="simulation"/>
      </FileInfo>
    </File>
    <File Path="$PGENDIR/sources_1/bd/Demodulator_over/hdl/Demodulator_over_wrapper.v">
      <FileInfo>
        <Attr Name="AutoDisabled" Val="1"/>
        <Attr Name="UsedIn" Val="synthesis"/>
        <Attr Name="UsedIn" Val="implementation"/>
        <Attr Name="UsedIn" Val="simulation"/>
      </FileInfo>
    </File>
    <File Path="$PSRCDIR/sources_1/new/demodulator.vhd">
      <FileInfo>
        <Attr Name="AutoDisabled" Val="1"/>
        <Attr Name="UsedIn" Val="synthesis"/>
        <Attr Name="UsedIn" Val="simulation"/>
      </FileInfo>
    </File>
    <File Path="$PSRCDIR/sources_1/new/modulator.vhd">
      <FileInfo>
        <Attr Name="AutoDisabled" Val="1"/>
        <Attr Name="UsedIn" Val="synthesis"/>
        <Attr Name="UsedIn" Val="simulation"/>
      </FileInfo>
    </File>
    <File Path="$PSRCDIR/sources_1/new/Data_splitter.vhd">
      <FileInfo>
        <Attr Name="AutoDisabled" Val="1"/>
        <Attr Name="UsedIn" Val="synthesis"/>
        <Attr Name="UsedIn" Val="simulation"/>
      </FileInfo>
    </File>
    <File Path="$PSRCDIR/sources_1/bd/Complete_module/Complete_module.bd">
      <FileInfo>
        <Attr Name="AutoDisabled" Val="1"/>
        <Attr Name="UsedIn" Val="synthesis"/>
        <Attr Name="UsedIn" Val="implementation"/>
        <Attr Name="UsedIn" Val="simulation"/>
      </FileInfo>
    </File>
    <Config>
      <Option Name="DesignMode" Val="RTL"/>
      <Option Name="TopModule" Val="Block_correctionV2_wrapper"/>
    </Config>
  </FileSet>
  <FileSet Name="constrs_in" Type="Constrs" RelSrcDir="$PSRCDIR/constrs_1" RelGenDir="$PGENDIR/constrs_1">
    <Filter Type="Constrs"/>
    <Config>
      <Option Name="ConstrsType" Val="XDC"/>
    </Config>
  </FileSet>
  <FileSet Name="utils" Type="Utils" RelSrcDir="$PSRCDIR/utils_1" RelGenDir="$PGENDIR/utils_1">
    <Filter Type="Utils"/>
    <File Path="$PSRCDIR/utils_1/imports/synth_1/Block_correctionV2_wrapper.dcp">
      <FileInfo>
        <Attr Name="UsedIn" Val="synthesis"/>
        <Attr Name="UsedIn" Val="implementation"/>
        <Attr Name="UsedInSteps" Val="synth_1"/>
        <Attr Name="AutoDcp" Val="1"/>
      </FileInfo>
    </File>
    <Config>
      <Option Name="TopAutoSet" Val="TRUE"/>
    </Config>
  </FileSet>
  <Strategy Version="1" Minor="2">
    <StratHandle Name="Vivado Synthesis Defaults" Flow="Vivado Synthesis 2023">
      <Desc>Vivado Synthesis Defaults</Desc>
    </StratHandle>
    <Step Id="synth_design"/>
  </Strategy>
  <BlockFileSet Type="BlockSrcs" Name="Block_correctionV2_find_error_0_0"/>
  <BlockFileSet Type="BlockSrcs" Name="Block_correctionV2_Input_memmory_0_0"/>
  <BlockFileSet Type="BlockSrcs" Name="Block_correctionV2_ControllerV2_0_0"/>
  <BlockFileSet Type="BlockSrcs" Name="Block_correctionV2_Output_memmory_0_0"/>
  <BlockFileSet Type="BlockSrcs" Name="Block_correctionV2_calc_parity_0_0"/>
  <BlockFileSet Type="BlockSrcs" Name="Block_correctionV2_correct_error_0_0"/>
</GenRun>
